kelly/__init__.py
kelly/core.py
kelly-1.0.dist-info/LICENSE.txt
kelly-1.0.dist-info/METADATA
kelly-1.0.dist-info/WHEEL
kelly-1.0.dist-info/top_level.txt
kelly-1.0.dist-info/RECORD
